AUTHORS
CHANGELOG.txt
DESCRIPTION
LICENSE
MANIFEST.in
README.rst
setup.py
django_localized_names.egg-info/PKG-INFO
django_localized_names.egg-info/SOURCES.txt
django_localized_names.egg-info/dependency_links.txt
django_localized_names.egg-info/requires.txt
django_localized_names.egg-info/top_level.txt
localized_names/__init__.py
localized_names/models.py
localized_names/formats/__init__.py
localized_names/formats/de/__init__.py
localized_names/formats/de/formats.py
localized_names/formats/en/__init__.py
localized_names/formats/en/formats.py
localized_names/formats/zh/__init__.py
localized_names/formats/zh/formats.py
localized_names/templatetags/__init__.py
localized_names/templatetags/localized_names_tags.py
localized_names/tests/__init__.py
localized_names/tests/localized_names_tags_tests.py
localized_names/tests/settings.py
localized_names/tests/test_settings.py
localized_names/tests/urls.py
localized_names/tests/test_app/__init__.py
localized_names/tests/test_app/models.py