Metadata-Version: 1.0
Name: django-localized-names
Version: 0.2.1
Summary: A reusable Django app to provide a correct order for names according to the
